{
  "resourceType": "Bundle",
  "id": "undefined",
  "type": "collection",
  "entry": [
    {
      "fullUrl": "/Composition/qE2cKcaPMtqGata3p",
      "resource": {
        "resourceType": "Composition",
        "id": "Composition1",
        "status": "preliminary",
        "subject": {
          "reference": "Patient/JohnDoe",
          "display": "John Doe"
        },
        "date": "2022-01-01",
        "author": [
          {
            "reference": "gkneWsGuDW5vE8Ryi",
            "display": "Allison Camron"
          }
        ],
        "title": "Continuity of Care Document",
        "confidentiality": "0",
        "type": {
          "coding": [
            {
              "system": "http://loinc.org",
              "display": "Physician Discharge summary",
              "code": "11490-0"
            }
          ]
        }
      }
    },
    {
      "fullUrl": "/Goal/7afmbB8HYhcNt2R4e",
      "resource": {
        "resourceType": "Goal",
        "id": "7afmbB8HYhcNt2R4e",
        "description": {
          "text": "Achieve blood glucose control – aiming at fasting blood glucose level below 108 mg/dl; HbA1c below 7%"
        },
        "priority": {
          "text": "medium"
        },
        "subject": {
          "display": "John Doe",
          "reference": "Patient/JohnDoe"
        },
        "lifecycleStatus": "active"
      }
    },
    {
      "fullUrl": "/Goal/cFiofX3mEeq9sCDpq",
      "resource": {
        "resourceType": "Goal",
        "id": "cFiofX3mEeq9sCDpq",
        "description": {
          "text": "Fasting blood glucose level below 108 mg/dl"
        },
        "priority": {
          "text": "medium"
        },
        "subject": {
          "display": "John Doe",
          "reference": "Patient/JohnDoe"
        },
        "lifecycleStatus": "active"
      }
    },
    {
      "fullUrl": "/Goal/4LzDoMCNzPhw6xncJ",
      "resource": {
        "resourceType": "Goal",
        "id": "4LzDoMCNzPhw6xncJ",
        "description": {
          "text": "Conformance to optimized diabetic diet"
        },
        "priority": {
          "text": "medium"
        },
        "subject": {
          "display": "John Doe",
          "reference": "Patient/JohnDoe"
        },
        "lifecycleStatus": "active"
      }
    },
    {
      "fullUrl": "/Goal/uLYQAaSNcyA353HtH",
      "resource": {
        "resourceType": "Goal",
        "id": "uLYQAaSNcyA353HtH",
        "description": {
          "text": "Achieve 0.5% body weight reduction (on current weight of 204 lb) per week to 160-175lb (BMI 24-25))"
        },
        "priority": {
          "text": "medium"
        },
        "subject": {
          "display": "John Doe",
          "reference": "Patient/JohnDoe"
        },
        "lifecycleStatus": "active"
      }
    },
    {
      "fullUrl": "/Goal/QMp5ew6uTSbu5pQ4C",
      "resource": {
        "resourceType": "Goal",
        "id": "QMp5ew6uTSbu5pQ4C",
        "description": {
          "text": "Improve and maintenance of optimal foot health; Prevention of diabetic foot ulcer, gangrene"
        },
        "priority": {
          "text": "medium"
        },
        "subject": {
          "display": "John Doe",
          "reference": "Patient/JohnDoe"
        },
        "lifecycleStatus": "active"
      }
    },
    {
      "fullUrl": "/Goal/Z8bznDhkG7g9dZ29Y",
      "resource": {
        "resourceType": "Goal",
        "id": "Z8bznDhkG7g9dZ29Y",
        "description": {
          "text": "Maintain blood pressure control with blood pressure readings below 140/90 mm Hg"
        },
        "priority": {
          "text": "medium"
        },
        "subject": {
          "display": "John Doe",
          "reference": "Patient/JohnDoe"
        },
        "lifecycleStatus": "active"
      }
    },
    {
      "fullUrl": "/Goal/zHDYtrFC5drLRnMEm",
      "resource": {
        "resourceType": "Goal",
        "id": "zHDYtrFC5drLRnMEm",
        "description": {
          "text": "Address patient knowledge deficit on diabetic self-care."
        },
        "priority": {
          "text": "medium"
        },
        "subject": {
          "display": "John Doe",
          "reference": "Patient/JohnDoe"
        },
        "lifecycleStatus": "active"
      }
    }
  ]
}
