{
  "resourceType": "StructureDefinition",
  "id": "MyImagingStudy",
  "extension": [
    {
      "url": "http://hl7.org/fhir/StructureDefinition/structuredefinition-category",
      "valueString": "Clinical.Diagnostics"
    },
    {
      "url": "http://hl7.org/fhir/StructureDefinition/structuredefinition-security-category",
      "valueCode": "patient"
    }
  ],
  "url": "https://gitlab.mitre.org/awatson/hello-implementation-guide/StructureDefinition/MyImagingStudy",
  "version": "0.2.0",
  "name": "MyImagingStudy",
  "status": "active",
  "description": "An example profile of the ImagingStudy resource.",
  "fhirVersion": "4.0.1",
  "mapping": [
    {
      "identity": "workflow",
      "uri": "http://hl7.org/fhir/workflow",
      "name": "Workflow Pattern"
    },
    {
      "identity": "rim",
      "uri": "http://hl7.org/v3",
      "name": "RIM Mapping"
    },
    {
      "identity": "dicom",
      "uri": "http://nema.org/dicom",
      "name": "DICOM Tag Mapping"
    },
    {
      "identity": "w5",
      "uri": "http://hl7.org/fhir/fivews",
      "name": "FiveWs Pattern Mapping"
    },
    {
      "identity": "v2",
      "uri": "http://hl7.org/v2",
      "name": "HL7 v2 Mapping"
    }
  ],
  "kind": "resource",
  "abstract": false,
  "type": "ImagingStudy",
  "baseDefinition": "http://hl7.org/fhir/StructureDefinition/ImagingStudy",
  "derivation": "constraint",
  "differential": {
    "element": [
      {
        "id": "ImagingStudy",
        "path": "ImagingStudy"
      }
    ]
  }
}
